{
  "timestamp": "2026-01-02T09:37:05Z",
  "recentCommits": [
    {
      "hash": "e4f3967",
      "subject": "chore: update dashboard data [skip ci]",
      "author": "Dashboard Bot",
      "date": "15 minutes ago"
    }
,
    {
      "hash": "26347b0",
      "subject": "chore: update dashboard data [skip ci]",
      "author": "Dashboard Bot",
      "date": "33 minutes ago"
    }
,
    {
      "hash": "54c8f63",
      "subject": "chore: update dashboard data [skip ci]",
      "author": "Dashboard Bot",
      "date": "15 hours ago"
    }
,
    {
      "hash": "169fb1f",
      "subject": "chore: update dashboard data [skip ci]",
      "author": "Dashboard Bot",
      "date": "15 hours ago"
    }
,
    {
      "hash": "10d5626",
      "subject": "chore: update dashboard data [skip ci]",
      "author": "Dashboard Bot",
      "date": "15 hours ago"
    }
,
    {
      "hash": "d78c847",
      "subject": "chore: update dashboard data [skip ci]",
      "author": "Dashboard Bot",
      "date": "16 hours ago"
    }
,
    {
      "hash": "5decc58",
      "subject": "chore: update dashboard data [skip ci]",
      "author": "Dashboard Bot",
      "date": "16 hours ago"
    }
,
    {
      "hash": "ce9911f",
      "subject": "chore: update dashboard data [skip ci]",
      "author": "Dashboard Bot",
      "date": "16 hours ago"
    }
,
    {
      "hash": "e5181ab",
      "subject": "chore: update dashboard data [skip ci]",
      "author": "Dashboard Bot",
      "date": "16 hours ago"
    }
,
    {
      "hash": "5ed7a9a",
      "subject": "chore: update dashboard data [skip ci]",
      "author": "Dashboard Bot",
      "date": "17 hours ago"
    }

  ]
}
