{
  "timestamp": "2025-12-19T10:02:38Z",
  "recentCommits": [
    {
      "hash": "46459e1",
      "subject": "chore: update dashboard data [skip ci]",
      "author": "Dashboard Bot",
      "date": "14 minutes ago"
    }
,
    {
      "hash": "ba7ffca",
      "subject": "chore: update dashboard data [skip ci]",
      "author": "Dashboard Bot",
      "date": "26 minutes ago"
    }
,
    {
      "hash": "63e82c0",
      "subject": "chore: update dashboard data [skip ci]",
      "author": "Dashboard Bot",
      "date": "40 minutes ago"
    }
,
    {
      "hash": "540534c",
      "subject": "chore: update dashboard data [skip ci]",
      "author": "Dashboard Bot",
      "date": "59 minutes ago"
    }
,
    {
      "hash": "c5dc8e9",
      "subject": "chore: update dashboard data [skip ci]",
      "author": "Dashboard Bot",
      "date": "15 hours ago"
    }
,
    {
      "hash": "895cfaf",
      "subject": "chore: update dashboard data [skip ci]",
      "author": "Dashboard Bot",
      "date": "15 hours ago"
    }
,
    {
      "hash": "d3f982b",
      "subject": "chore: update dashboard data [skip ci]",
      "author": "Dashboard Bot",
      "date": "16 hours ago"
    }
,
    {
      "hash": "8575b5f",
      "subject": "chore: update dashboard data [skip ci]",
      "author": "Dashboard Bot",
      "date": "16 hours ago"
    }
,
    {
      "hash": "bbb862c",
      "subject": "chore: update dashboard data [skip ci]",
      "author": "Dashboard Bot",
      "date": "16 hours ago"
    }
,
    {
      "hash": "0aec994",
      "subject": "chore: update dashboard data [skip ci]",
      "author": "Dashboard Bot",
      "date": "16 hours ago"
    }

  ]
}
