{
  "timestamp": "2025-12-19T11:33:25Z",
  "recentCommits": [
    {
      "hash": "a6bf319",
      "subject": "chore: update dashboard data [skip ci]",
      "author": "Dashboard Bot",
      "date": "12 minutes ago"
    }
,
    {
      "hash": "c3d0c04",
      "subject": "chore: update dashboard data [skip ci]",
      "author": "Dashboard Bot",
      "date": "31 minutes ago"
    }
,
    {
      "hash": "6fe201e",
      "subject": "chore: update dashboard data [skip ci]",
      "author": "Dashboard Bot",
      "date": "43 minutes ago"
    }
,
    {
      "hash": "fdafebf",
      "subject": "chore: update dashboard data [skip ci]",
      "author": "Dashboard Bot",
      "date": "55 minutes ago"
    }
,
    {
      "hash": "4e8f5f1",
      "subject": "chore: update dashboard data [skip ci]",
      "author": "Dashboard Bot",
      "date": "71 minutes ago"
    }
,
    {
      "hash": "a2e757e",
      "subject": "chore: update dashboard data [skip ci]",
      "author": "Dashboard Bot",
      "date": "2 hours ago"
    }
,
    {
      "hash": "46459e1",
      "subject": "chore: update dashboard data [skip ci]",
      "author": "Dashboard Bot",
      "date": "2 hours ago"
    }
,
    {
      "hash": "ba7ffca",
      "subject": "chore: update dashboard data [skip ci]",
      "author": "Dashboard Bot",
      "date": "2 hours ago"
    }
,
    {
      "hash": "63e82c0",
      "subject": "chore: update dashboard data [skip ci]",
      "author": "Dashboard Bot",
      "date": "2 hours ago"
    }
,
    {
      "hash": "540534c",
      "subject": "chore: update dashboard data [skip ci]",
      "author": "Dashboard Bot",
      "date": "3 hours ago"
    }

  ]
}
