{
  "timestamp": "2025-12-16T11:21:41Z",
  "recentCommits": [
    {
      "hash": "01df683",
      "subject": "chore: update dashboard data [skip ci]",
      "author": "Dashboard Bot",
      "date": "19 minutes ago"
    }
,
    {
      "hash": "63a27d5",
      "subject": "chore: update dashboard data [skip ci]",
      "author": "Dashboard Bot",
      "date": "31 minutes ago"
    }
,
    {
      "hash": "9cba8d4",
      "subject": "chore: update dashboard data [skip ci]",
      "author": "Dashboard Bot",
      "date": "42 minutes ago"
    }
,
    {
      "hash": "b0a05d5",
      "subject": "chore: update dashboard data [skip ci]",
      "author": "Dashboard Bot",
      "date": "59 minutes ago"
    }
,
    {
      "hash": "68656aa",
      "subject": "chore: update dashboard data [skip ci]",
      "author": "Dashboard Bot",
      "date": "79 minutes ago"
    }
,
    {
      "hash": "5512cfe",
      "subject": "chore: update dashboard data [skip ci]",
      "author": "Dashboard Bot",
      "date": "2 hours ago"
    }
,
    {
      "hash": "f38b017",
      "subject": "chore: update dashboard data [skip ci]",
      "author": "Dashboard Bot",
      "date": "2 hours ago"
    }
,
    {
      "hash": "33c8de6",
      "subject": "chore: update dashboard data [skip ci]",
      "author": "Dashboard Bot",
      "date": "2 hours ago"
    }
,
    {
      "hash": "3689e79",
      "subject": "chore: update dashboard data [skip ci]",
      "author": "Dashboard Bot",
      "date": "2 hours ago"
    }
,
    {
      "hash": "78bb9b0",
      "subject": "chore: update dashboard data [skip ci]",
      "author": "Dashboard Bot",
      "date": "16 hours ago"
    }

  ]
}
