{
  "timestamp": "2025-12-02T10:38:38Z",
  "recentCommits": [
    {
      "hash": "f00cc2d",
      "subject": "chore: update dashboard data [skip ci]",
      "author": "Dashboard Bot",
      "date": "16 minutes ago"
    }
,
    {
      "hash": "5903649",
      "subject": "chore: update dashboard data [skip ci]",
      "author": "Dashboard Bot",
      "date": "36 minutes ago"
    }
,
    {
      "hash": "83ecc44",
      "subject": "chore: update dashboard data [skip ci]",
      "author": "Dashboard Bot",
      "date": "48 minutes ago"
    }
,
    {
      "hash": "9a85b86",
      "subject": "chore: update dashboard data [skip ci]",
      "author": "Dashboard Bot",
      "date": "60 minutes ago"
    }
,
    {
      "hash": "583573a",
      "subject": "chore: update dashboard data [skip ci]",
      "author": "Dashboard Bot",
      "date": "76 minutes ago"
    }
,
    {
      "hash": "14c84f9",
      "subject": "chore: update dashboard data [skip ci]",
      "author": "Dashboard Bot",
      "date": "2 hours ago"
    }
,
    {
      "hash": "6901b70",
      "subject": "chore: update dashboard data [skip ci]",
      "author": "Dashboard Bot",
      "date": "16 hours ago"
    }
,
    {
      "hash": "a93f274",
      "subject": "chore: update dashboard data [skip ci]",
      "author": "Dashboard Bot",
      "date": "16 hours ago"
    }
,
    {
      "hash": "665aacb",
      "subject": "chore: update dashboard data [skip ci]",
      "author": "Dashboard Bot",
      "date": "16 hours ago"
    }
,
    {
      "hash": "90fc0c4",
      "subject": "chore: update dashboard data [skip ci]",
      "author": "Dashboard Bot",
      "date": "17 hours ago"
    }

  ]
}
