{
  "timestamp": "2025-12-26T10:21:59Z",
  "recentCommits": [
    {
      "hash": "8e9fec5",
      "subject": "chore: update dashboard data [skip ci]",
      "author": "Dashboard Bot",
      "date": "19 minutes ago"
    }
,
    {
      "hash": "59910e3",
      "subject": "chore: update dashboard data [skip ci]",
      "author": "Dashboard Bot",
      "date": "34 minutes ago"
    }
,
    {
      "hash": "2a7f21e",
      "subject": "chore: update dashboard data [skip ci]",
      "author": "Dashboard Bot",
      "date": "46 minutes ago"
    }
,
    {
      "hash": "56e9827",
      "subject": "chore: update dashboard data [skip ci]",
      "author": "Dashboard Bot",
      "date": "60 minutes ago"
    }
,
    {
      "hash": "5c48139",
      "subject": "chore: update dashboard data [skip ci]",
      "author": "Dashboard Bot",
      "date": "79 minutes ago"
    }
,
    {
      "hash": "9fd2b20",
      "subject": "chore: update dashboard data [skip ci]",
      "author": "Dashboard Bot",
      "date": "16 hours ago"
    }
,
    {
      "hash": "ba1628e",
      "subject": "chore: update dashboard data [skip ci]",
      "author": "Dashboard Bot",
      "date": "16 hours ago"
    }
,
    {
      "hash": "fe532e8",
      "subject": "chore: update dashboard data [skip ci]",
      "author": "Dashboard Bot",
      "date": "16 hours ago"
    }
,
    {
      "hash": "e41111a",
      "subject": "chore: update dashboard data [skip ci]",
      "author": "Dashboard Bot",
      "date": "16 hours ago"
    }
,
    {
      "hash": "64e3a72",
      "subject": "chore: update dashboard data [skip ci]",
      "author": "Dashboard Bot",
      "date": "17 hours ago"
    }

  ]
}
